{
    "ciphers": {
        "DHE_DSS_AES_128_CBC_SHA1": 4,
        "DHE_RSA_AES_128_CBC_SHA1": 68,
        "DHE_RSA_AES_128_GCM_SHA256": 658,
        "DHE_RSA_AES_256_CBC_SHA1": 2064,
        "DHE_RSA_AES_256_CBC_SHA256": 116793,
        "DHE_RSA_CAMELLIA_256_CBC_SHA1": 3813,
        "ECDHE_ECDSA_AES_128_GCM_SHA256": 47,
        "ECDHE_RSA_3DES_EDE_CBC_SHA1": 15,
        "ECDHE_RSA_AES_128_CBC_SHA1": 23948,
        "ECDHE_RSA_AES_128_CBC_SHA256": 2996228,
        "ECDHE_RSA_AES_128_GCM_SHA256": 8674415,
        "ECDHE_RSA_AES_256_CBC_SHA1": 6030,
        "ECDHE_RSA_AES_256_GCM_SHA384": 36297,
        "RSA_3DES_EDE_CBC_SHA1": 357,
        "RSA_AES_128_CBC_SHA1": 356309,
        "RSA_AES_128_CBC_SHA256": 206,
        "RSA_AES_128_GCM_SHA256": 318150,
        "RSA_AES_256_CBC_SHA1": 129,
        "RSA_AES_256_CBC_SHA256": 3501,
        "RSA_ARCFOUR_128_MD5": 381,
        "RSA_ARCFOUR_128_SHA1": 20896
    },
    "counts": {
        "non_tls": 589973,
        "tls": 12560309,
        "tls_nonpfs": 699929,
        "tls_pfs": 11860380,
        "total": 13150282
    },
    "now": 1463183942,
    "proto": {
        "TLS1.0": 274049,
        "TLS1.1": 1056,
        "TLS1.2": 12285204
    }
}
