{
    "ciphers": {
        "DHE_DSS_AES_128_CBC_SHA1": 1,
        "DHE_RSA_AES_128_CBC_SHA1": 71,
        "DHE_RSA_AES_128_GCM_SHA256": 633,
        "DHE_RSA_AES_256_CBC_SHA1": 1828,
        "DHE_RSA_AES_256_CBC_SHA256": 108490,
        "DHE_RSA_CAMELLIA_256_CBC_SHA1": 3119,
        "ECDHE_ECDSA_AES_128_GCM_SHA256": 32,
        "ECDHE_RSA_3DES_EDE_CBC_SHA1": 9,
        "ECDHE_RSA_AES_128_CBC_SHA1": 21373,
        "ECDHE_RSA_AES_128_CBC_SHA256": 2321892,
        "ECDHE_RSA_AES_128_GCM_SHA256": 7443511,
        "ECDHE_RSA_AES_256_CBC_SHA1": 5109,
        "ECDHE_RSA_AES_256_GCM_SHA384": 33856,
        "RSA_3DES_EDE_CBC_SHA1": 355,
        "RSA_AES_128_CBC_SHA1": 263849,
        "RSA_AES_128_CBC_SHA256": 181,
        "RSA_AES_128_GCM_SHA256": 314793,
        "RSA_AES_256_CBC_SHA1": 137,
        "RSA_AES_256_CBC_SHA256": 3215,
        "RSA_ARCFOUR_128_MD5": 298,
        "RSA_ARCFOUR_128_SHA1": 22718,
        "RSA_CAMELLIA_128_CBC_SHA1": 1
    },
    "counts": {
        "non_tls": 526099,
        "tls": 10545471,
        "tls_nonpfs": 605547,
        "tls_pfs": 9939924,
        "total": 11071570
    },
    "now": 1465084741,
    "proto": {
        "TLS1.0": 220157,
        "TLS1.1": 913,
        "TLS1.2": 10324401
    }
}
